CHANGELOG
LICENSE
MANIFEST.in
README.rst
pyproject.toml
requirements.txt
setup.cfg
setup.py
versioneer.py
src/webdrivermanager/__init__.py
src/webdrivermanager/__main__.py
src/webdrivermanager/_version.py
src/webdrivermanager/base.py
src/webdrivermanager/chrome.py
src/webdrivermanager/edge.py
src/webdrivermanager/edgechromium.py
src/webdrivermanager/gecko.py
src/webdrivermanager/ie.py
src/webdrivermanager/misc.py
src/webdrivermanager/opera.py
src/webdrivermanager.egg-info/PKG-INFO
src/webdrivermanager.egg-info/SOURCES.txt
src/webdrivermanager.egg-info/dependency_links.txt
src/webdrivermanager.egg-info/entry_points.txt
src/webdrivermanager.egg-info/not-zip-safe
src/webdrivermanager.egg-info/requires.txt
src/webdrivermanager.egg-info/top_level.txt